crazylog/__init__.py
crazylog/crazy_logger.py
crazylog/module_dec.py
crazylog-0.1.1.dist-info/LICENSE
crazylog-0.1.1.dist-info/METADATA
crazylog-0.1.1.dist-info/WHEEL
crazylog-0.1.1.dist-info/top_level.txt
crazylog-0.1.1.dist-info/RECORD
