Metadata-Version: 2.1
Name: crazylog
Version: 0.1.1
Summary: A Python package to add extensive logs to each execution statement
Home-page: https://github.com/afarntrog/crazylog
Author: Aaron Farntrog
License: MIT
Keywords: log logging debug monitor python3 python
Platform: UNKNOWN
Classifier: Programming Language :: Python :: 3
Classifier: License :: OSI Approved :: MIT License
Classifier: Operating System :: OS Independent
Requires-Python: >=3.6
